aiomothr/__init__.py
aiomothr/client.py
aiomothr/request.py
aiomothr/schema.graphql
aiomothr-0.3.0.dist-info/LICENSE
aiomothr-0.3.0.dist-info/METADATA
aiomothr-0.3.0.dist-info/WHEEL
aiomothr-0.3.0.dist-info/top_level.txt
aiomothr-0.3.0.dist-info/RECORD
