Metadata-Version: 2.1
Name: aiomothr
Version: 0.3.0
Summary: Asynchronous client library for interacting with MOTHR
Home-page: https://github.com/rs21io/aiomothr
Author: James Arnold
Author-email: james@rs21.io
License: UNKNOWN
Platform: UNKNOWN
Classifier: Programming Language :: Python :: 3
Classifier: License :: OSI Approved :: BSD License
Classifier: Operating System :: OS Independent
Requires-Python: >=3.6
Requires-Dist: gql[aiohttp,websockets] (==3.0.0a4)
Provides-Extra: dev
Requires-Dist: asynctest ; extra == 'dev'
Requires-Dist: pytest ; extra == 'dev'
Requires-Dist: pytest-asyncio ; extra == 'dev'
Requires-Dist: pytest-cov ; extra == 'dev'
Requires-Dist: pytest-mypy ; extra == 'dev'
Requires-Dist: pytest-pylint ; extra == 'dev'
